nameko_tracer/__init__.py
nameko_tracer/adapters.py
nameko_tracer/constants.py
nameko_tracer/dependency.py
nameko_tracer/filters.py
nameko_tracer/formatters.py
nameko_tracer/utils.py
nameko_tracer-1.4.0.dist-info/LICENSE
nameko_tracer-1.4.0.dist-info/METADATA
nameko_tracer-1.4.0.dist-info/WHEEL
nameko_tracer-1.4.0.dist-info/top_level.txt
nameko_tracer-1.4.0.dist-info/zip-safe
nameko_tracer-1.4.0.dist-info/RECORD
