Metadata-Version: 2.1
Name: nameko-tracer
Version: 1.4.0
Summary: Nameko extension logging entrypoint processing metrics
Home-page: https://github.com/nameko/nameko-tracer
Author: student.com
Author-email: wearehiring@student.com
License: Apache License, Version 2.0
Platform: UNKNOWN
License-File: LICENSE
Requires-Dist: nameko (>=2.8.5)
Provides-Extra: dev
Requires-Dist: coverage ; extra == 'dev'
Requires-Dist: flake8 ; extra == 'dev'
Requires-Dist: pylint ; extra == 'dev'
Requires-Dist: pytest ; extra == 'dev'
